fa2rs/__init__.py
fa2rs/__test__.py
fa2rs/libfa2rs.so
fa2rs-0.3.2.dist-info/LICENSE
fa2rs-0.3.2.dist-info/METADATA
fa2rs-0.3.2.dist-info/WHEEL
fa2rs-0.3.2.dist-info/top_level.txt
fa2rs-0.3.2.dist-info/RECORD
