Metadata-Version: 2.1
Name: fa2rs
Version: 0.3.2
Summary: Bindings to full Rust ForceAtlas2 implementation
Home-page: https://framagit.org/ZettaScript/fa2rs-py
Author: Pascal Engélibert
Author-email: tuxmain@zettascript.org
License: UNKNOWN
Keywords: forceatlas2 graph force-directed-graph force-layout
Platform: UNKNOWN
Classifier: Programming Language :: Python :: 3
Classifier: License :: OSI Approved :: GNU Affero General Public License v3
Classifier: Operating System :: OS Independent
Classifier: Topic :: Scientific/Engineering :: Mathematics
Requires-Python: >=3.6
